{
  "1001": {
    "name": "str",
    "defaultValue": 0.0,
    "minValue": 0.0,
    "validModifierIDs": [2005,2015,2017],
    "formulaParts": 9
  },
  "1002": {
    "name": "agi",
    "defaultValue": 0.0,
    "minValue": 0.0,
    "validModifierIDs": [2006],
    "formulaParts": 9
  },
  "1003": {
    "name": "wis",
    "defaultValue": 0.0,
    "minValue": 0.0,
    "validModifierIDs": [2007,2037,2039],
    "formulaParts": 9
  },
  "1004": {
    "name": "luck",
    "defaultValue": 0.0,
    "minValue": 0.0,
    "validModifierIDs": [2008],
    "formulaParts": 9
  },
  "1005": {
    "name": "accuracy",
    "defaultValue": 2.0,
    "minValue": 0.0,
    "validModifierIDs": [],
    "formulaParts": 9
  },
  "1006": {
    "name": "mastery",
    "defaultValue": 0.35,
    "minValue": 0.0,
    "validModifierIDs": [],
    "formulaParts": 9
  },
  "1007": {
    "name": "weaponPower",
    "defaultValue": 0.0,
    "minValue": 0.0,
    "validModifierIDs": [],
    "formulaParts": 9
  },
  "1008": {
    "name": "unarmedWeaponPower",
    "defaultValue": 5.0,
    "minValue": 0.0,
    "validModifierIDs": [],
    "formulaParts": 9
  },
  "1009": {
    "name": "defense",
    "defaultValue": 0.0,
    "minValue": 0.0,
    "validModifierIDs": [2003],
    "formulaParts": 9
  },
  "1010": {
    "name": "hp",
    "defaultValue": 10.0,
    "minValue": 0.0,
    "validModifierIDs": [],
    "formulaParts": 9
  },
  "1011": {
    "name": "maxHp",
    "defaultValue": 10.0,
    "minValue": 0.0,
    "validModifierIDs": [2001,2012],
    "formulaParts": 9
  },
  "1012": {
    "name": "mp",
    "defaultValue": 5.0,
    "minValue": 0.0,
    "validModifierIDs": [],
    "formulaParts": 9
  },
  "1013": {
    "name": "maxMp",
    "defaultValue": 5.0,
    "minValue": 0.0,
    "validModifierIDs": [2002,2034],
    "formulaParts": 9
  },
  "1014": {
    "name": "damageFlatBonus",
    "defaultValue": 0.0,
    "minValue": 0.0,
    "validModifierIDs": [2004],
    "formulaParts": 9
  },
  "1015": {
    "name": "damageMultiplier",
    "defaultValue": 1.0,
    "minValue": 0.0,
    "validModifierIDs": [2009],
    "formulaParts": 9
  },
  "1016": {
    "name": "critChance",
    "defaultValue": 0.025,
    "minValue": 0.0,
    "validModifierIDs": [2011],
    "formulaParts": 9
  },
  "1017": {
    "name": "critDamage",
    "defaultValue": 0.0,
    "minValue": 0.0,
    "validModifierIDs": [2011],
    "formulaParts": 9
  },
  "1018": {
    "name": "bossDamage",
    "defaultValue": 0.0,
    "minValue": 0.0,
    "validModifierIDs": [],
    "formulaParts": 9
  },
  "1019": {
    "name": "dropRate",
    "defaultValue": 0.0,
    "minValue": 0.0,
    "validModifierIDs": [],
    "formulaParts": 9
  },
  "1020": {
    "name": "classXPRate",
    "defaultValue": 0.0,
    "minValue": 0.0,
    "validModifierIDs": [],
    "formulaParts": 9
  },
  "1021": {
    "name": "speed",
    "defaultValue": 5.0,
    "minValue": 0.0,
    "validModifierIDs": [],
    "formulaParts": 9
  },
  "1022": {
    "name": "damage",
    "defaultValue": 0.0,
    "minValue": 0.0,
    "validModifierIDs": [2010,2036,2038,2014,2016],
    "formulaParts": 10
  }
}
